iiot_openapi/__init__.py
iiot_openapi/api_client.py
iiot_openapi/api_response.py
iiot_openapi/configuration.py
iiot_openapi/exceptions.py
iiot_openapi/py.typed
iiot_openapi/rest.py
iiot_openapi/api/__init__.py
iiot_openapi/api/default_api.py
iiot_openapi/api/model_api.py
iiot_openapi/api/record_api.py
iiot_openapi/api/table_api.py
iiot_openapi/models/__init__.py
iiot_openapi/models/add_view_nodes_req.py
iiot_openapi/models/aging_settings.py
iiot_openapi/models/analysis_task.py
iiot_openapi/models/analysis_task_list_rsp.py
iiot_openapi/models/attach_thing_req_dto.py
iiot_openapi/models/auth_info_dto.py
iiot_openapi/models/batch_list_thing_snapshots_req.py
iiot_openapi/models/batch_list_thing_snapshots_req_things_inner.py
iiot_openapi/models/batch_list_thing_snapshots_resp.py
iiot_openapi/models/batch_list_thing_snapshots_resp_things_inner.py
iiot_openapi/models/brief_analysis_task.py
iiot_openapi/models/brief_dictionary.py
iiot_openapi/models/brief_model.py
iiot_openapi/models/brief_process_settings.py
iiot_openapi/models/brief_table.py
iiot_openapi/models/brief_thing.py
iiot_openapi/models/brief_view.py
iiot_openapi/models/catalog.py
iiot_openapi/models/catalog_node.py
iiot_openapi/models/catalog_order.py
iiot_openapi/models/clean_analysis_settings_dto.py
iiot_openapi/models/clean_settings.py
iiot_openapi/models/column_schema.py
iiot_openapi/models/complex_analysis_settings_dto.py
iiot_openapi/models/complex_setting.py
iiot_openapi/models/component_dto.py
iiot_openapi/models/component_property.py
iiot_openapi/models/component_reference_conf_details.py
iiot_openapi/models/component_reference_conf_dto.py
iiot_openapi/models/create_analysis_task_req.py
iiot_openapi/models/create_catalog_req.py
iiot_openapi/models/create_device_req_dto.py
iiot_openapi/models/create_device_resp_dto.py
iiot_openapi/models/create_dictionary_req.py
iiot_openapi/models/create_model_request.py
iiot_openapi/models/create_table_request.py
iiot_openapi/models/create_thing_request.py
iiot_openapi-0.0.4.dist-info/METADATA
iiot_openapi-0.0.4.dist-info/WHEEL
iiot_openapi-0.0.4.dist-info/top_level.txt
iiot_openapi-0.0.4.dist-info/RECORD
